stock_analysis_toolkit/__init__.py
stock_analysis_toolkit/main.py
stock_analysis_toolkit/technical_analysis.py
stock_analysis_toolkit/analysis/__init__.py
stock_analysis_toolkit/analysis/bond.py
stock_analysis_toolkit/analysis/fundamental.py
stock_analysis_toolkit/analysis/mutual_fund_analyzer.py
stock_analysis_toolkit/analysis/technical.py
stock_analysis_toolkit/config/__init__.py
stock_analysis_toolkit/config/constants.py
stock_analysis_toolkit/config/settings.py
stock_analysis_toolkit/core/__init__.py
stock_analysis_toolkit/core/analyzer.py
stock_analysis_toolkit/core/models.py
stock_analysis_toolkit/data/__init__.py
stock_analysis_toolkit/data/alpha_vantage_fetcher.py
stock_analysis_toolkit/data/fetcher.py
stock_analysis_toolkit/data/marketstack_fetcher.py
stock_analysis_toolkit/data/models.py
stock_analysis_toolkit/data/mutual_fund_fetcher.py
stock_analysis_toolkit/data/screener_fetcher.py
stock_analysis_toolkit/data/storage.py
stock_analysis_toolkit/mutual_fund_analysis/__init__.py
stock_analysis_toolkit/mutual_fund_analysis/analyzer.py
stock_analysis_toolkit/mutual_fund_analysis/fetcher.py
stock_analysis_toolkit/reporting/__init__.py
stock_analysis_toolkit/reporting/email_sender.py
stock_analysis_toolkit/reporting/email_sender.py.backup
stock_analysis_toolkit/reporting/email_sender.py.bak
stock_analysis_toolkit/reporting/reporter.py
stock_analysis_toolkit/reporting/templates.py
stock_analysis_toolkit/reporting/templates/base.html
stock_analysis_toolkit/reporting/templates/email_template.html
stock_analysis_toolkit/reporting/templates/sector_report.html
stock_analysis_toolkit/reporting/templates/stock_report.html
stock_analysis_toolkit/templates/email_template_clean.html
stock_analysis_toolkit/templates/email_template_clean.html.bak
stock_analysis_toolkit/utils/__init__.py
stock_analysis_toolkit/utils/api_client.py
stock_analysis_toolkit/utils/cache.py
stock_analysis_toolkit/utils/file_utils.py
stock_analysis_toolkit/utils/logging_config.py
stock_analysis_toolkit-1.0.49.dist-info/METADATA
stock_analysis_toolkit-1.0.49.dist-info/WHEEL
stock_analysis_toolkit-1.0.49.dist-info/entry_points.txt
stock_analysis_toolkit-1.0.49.dist-info/top_level.txt
stock_analysis_toolkit-1.0.49.dist-info/RECORD
