Metadata-Version: 2.4
Name: stock-analysis-toolkit
Version: 1.0.49
Summary: A comprehensive toolkit for stock market analysis and reporting
Home-page: https://github.com/pranav87/stock_analysis
Author: Pranav Phalnikar
Author-email: Pranav Phalnikar <phalnikar.pranav@gmail.com>
License: MIT
Project-URL: Homepage, https://github.com/pranav87/stock_analysis
Project-URL: Documentation, https://github.com/pranav87/stock_analysis#readme
Project-URL: Issues, https://github.com/pranav87/stock_analysis/issues
Project-URL: Source, https://github.com/pranav87/stock_analysis
Keywords: stocks,trading,analysis,finance,investing
Classifier: Development Status :: 4 - Beta
Classifier: Intended Audience :: Financial and Insurance Industry
Classifier: Intended Audience :: Developers
Classifier: License :: OSI Approved :: MIT License
Classifier: Programming Language :: Python :: 3.10
Classifier: Programming Language :: Python :: 3.11
Classifier: Programming Language :: Python :: 3.12
Classifier: Topic :: Office/Business :: Financial :: Investment
Classifier: Topic :: Software Development :: Libraries :: Python Modules
Classifier: Operating System :: OS Independent
Requires-Python: >=3.10
Requires-Dist: pandas<3.0.0,>=1.5.0
Requires-Dist: numpy>=1.21.0
Requires-Dist: python-dateutil>=2.8.2
Requires-Dist: pytz>=2021.1
Requires-Dist: yfinance>=0.2.0
Requires-Dist: requests>=2.26.0
Requires-Dist: beautifulsoup4>=4.10.0
Requires-Dist: lxml>=4.6.3
Requires-Dist: matplotlib>=3.8.0
Requires-Dist: seaborn>=0.11.2
Requires-Dist: plotly>=5.3.1
Requires-Dist: python-dotenv>=0.19.0
Requires-Dist: pydantic>=1.8.2
Requires-Dist: pydantic-settings>=2.0.0
Requires-Dist: email-validator>=2.1.0
Requires-Dist: tqdm>=4.62.3
Requires-Dist: Jinja2>=3.0.0
Requires-Dist: html2text>=2020.1.16
Requires-Dist: kaleido>=0.2.1
Requires-Dist: rich>=13.0.0
Provides-Extra: full
Requires-Dist: TA-Lib>=0.4.24; platform_system != "Windows" and extra == "full"
Requires-Dist: pandas-ta>=0.3.14b0; extra == "full"
Requires-Dist: alpha_vantage>=2.3.1; extra == "full"
Requires-Dist: nsepy>=0.8; extra == "full"
Requires-Dist: nsetools>=1.1.8; extra == "full"
Requires-Dist: selenium>=4.1.0; extra == "full"
Requires-Dist: webdriver-manager>=3.8.0; extra == "full"
Requires-Dist: fastapi>=0.70.0; extra == "full"
Requires-Dist: uvicorn>=0.15.0; extra == "full"
Provides-Extra: dev
Requires-Dist: pytest>=7.0.0; extra == "dev"
Requires-Dist: pytest-cov>=4.0.0; extra == "dev"
Requires-Dist: black>=23.0.0; extra == "dev"
Requires-Dist: isort>=5.12.0; extra == "dev"
Requires-Dist: mypy>=1.0.0; extra == "dev"
Requires-Dist: flake8>=6.0.0; extra == "dev"
Requires-Dist: pre-commit>=3.0.0; extra == "dev"
Requires-Dist: build>=0.10.0; extra == "dev"
Requires-Dist: twine>=4.0.0; extra == "dev"
Requires-Dist: pandas-stubs>=2.0.0; extra == "dev"
Requires-Dist: types-requests>=2.0.0; extra == "dev"
Requires-Dist: types-seaborn>=0.13.0; extra == "dev"
Dynamic: author
Dynamic: home-page
Dynamic: requires-python
